MANIFEST.in
README.md
setup.py
uttut/__init__.py
uttut/__version__.py
uttut/elements.c
uttut/elements.pyx
uttut/entity_overlapping_ratio.py
uttut/exceptions.py
uttut/expand_by_entities.c
uttut/expand_by_entities.pyx
uttut/get_unique_entities.py
uttut/utils.py
uttut.egg-info/PKG-INFO
uttut.egg-info/SOURCES.txt
uttut.egg-info/dependency_links.txt
uttut.egg-info/top_level.txt
uttut/pipeline/__init__.py
uttut/pipeline/intermediate.py
uttut/pipeline/pipe.py
uttut/pipeline/utils.py
uttut/pipeline/bert/__init__.py
uttut/pipeline/bert/basic.py
uttut/pipeline/bert/full.py
uttut/pipeline/bert/word_piece.py
uttut/pipeline/bert/tests/__init__.py
uttut/pipeline/bert/tests/test_basic.py
uttut/pipeline/bert/tests/test_full.py
uttut/pipeline/bert/tests/test_word_piece.py
uttut/pipeline/bert/tests/tokenization.py
uttut/pipeline/edit/__init__.py
uttut/pipeline/edit/label_propagation.c
uttut/pipeline/edit/label_propagation.pyx
uttut/pipeline/edit/lst2lst.py
uttut/pipeline/edit/lst2str.py
uttut/pipeline/edit/replacement.c
uttut/pipeline/edit/replacement.pxd
uttut/pipeline/edit/replacement.pyx
uttut/pipeline/edit/span.c
uttut/pipeline/edit/span.pxd
uttut/pipeline/edit/span.pyx
uttut/pipeline/edit/str2lst.py
uttut/pipeline/edit/str2str.py
uttut/pipeline/edit/utils.c
uttut/pipeline/edit/utils.pyx
uttut/pipeline/edit/validation.c
uttut/pipeline/edit/validation.pxd
uttut/pipeline/edit/validation.pyx
uttut/pipeline/edit/tests/__init__.py
uttut/pipeline/edit/tests/test_label_propagation.py
uttut/pipeline/edit/tests/test_lst2lst.py
uttut/pipeline/edit/tests/test_replacement.py
uttut/pipeline/edit/tests/test_replacement_group.py
uttut/pipeline/edit/tests/test_span.py
uttut/pipeline/edit/tests/test_span_group.py
uttut/pipeline/edit/tests/test_str2lst.py
uttut/pipeline/edit/tests/test_str2str.py
uttut/pipeline/edit/tests/test_validate_start_end.py
uttut/pipeline/ops/__init__.py
uttut/pipeline/ops/add_end_token.py
uttut/pipeline/ops/add_sos_eos.py
uttut/pipeline/ops/add_whitespace_around_character.py
uttut/pipeline/ops/add_whitespace_around_cjk.py
uttut/pipeline/ops/add_whitespace_around_punctuation.py
