Metadata-Version: 2.1
Name: uttut
Version: 1.4.10
Summary: Yoctol Utterance processing utilities
Home-page: https://github.com/Yoctol/uttut
Author: cph
License: MIT
Platform: UNKNOWN
Classifier: Programming Language :: Python
Classifier: Programming Language :: Python :: 3.5
Classifier: Programming Language :: Python :: 3.6
Classifier: Development Status :: 3 - Alpha
Requires-Python: >=3.5
